{
  "appPageId" : "be495781-8c00-4d23-813c-9cb448fbef69",
  "componentName" : "siteforce:sldsTwoCol66Layout",
  "dataProviders" : [ ],
  "id" : "09e72f9f-457d-4049-9714-cd0881711d52",
  "label" : "Contact Us",
  "regions" : [ {
    "id" : "ce78776e-4662-477c-a484-0645e2df1541",
    "regionName" : "header",
    "type" : "region"
  }, {
    "components" : [ {
      "componentAttributes" : {
        "allowAttachments" : true,
        "attachmentLabel" : "Upload File",
        "buttonAlignment" : "center",
        "buttonBgColor" : "",
        "buttonBgHoverColor" : "",
        "buttonBorderColor" : "",
        "buttonMaxWidth" : "",
        "buttonRadius" : 0,
        "buttonTextColor" : "",
        "buttonTextHoverColor" : "",
        "callToAction" : false,
        "callToActionButtonText" : "",
        "callToActionText" : "",
        "callToActionUrl" : "",
        "confirmationSubtext" : "We’ll get back to you soon.",
        "confirmationText" : "Your case was created.",
        "guestQuickActionName" : "Select or configure a global action",
        "headerSubtitle" : "Tell us how we can help.",
        "headerTitle" : "Contact Customer Support",
        "isMicrobatch" : false,
        "quickActionName" : "NewCase",
        "requestSummaryText" : "Case summary"
      },
      "componentName" : "forceCommunity:contactSupportForm",
      "id" : "60394d9d-0c6d-4339-9fcf-f28b0dd2da34",
      "renderPriority" : "NEUTRAL",
      "renditionMap" : { },
      "type" : "component"
    } ],
    "id" : "3c09847c-7b05-4349-8f79-76f7d020f106",
    "regionName" : "content",
    "type" : "region"
  }, {
    "components" : [ {
      "componentAttributes" : {
        "askConfirmationQuestion" : true,
        "confirmationMessageLabel" : "Got it!",
        "deflectionSubtitle" : "Find what you need here.",
        "deflectionTitle" : "Need Answers Fast?",
        "firstQuestion" : "Did this content solve your issue?",
        "maxResults" : 6,
        "measureDeflection" : true,
        "redirectUrl" : "",
        "secondQuestion" : "Stop creating your case?",
        "showArticles" : true,
        "showDiscussions" : false,
        "topicId" : ""
      },
      "componentName" : "forceCommunity:caseDeflection",
      "id" : "f5b57bbf-9a1f-4fd0-91d0-a5b74f9f3020",
      "renderPriority" : "NEUTRAL",
      "renditionMap" : { },
      "type" : "component"
    } ],
    "id" : "08513ad8-bdc7-42a4-b71b-b4a5acddc8e5",
    "regionName" : "sidebar",
    "type" : "region"
  }, {
    "id" : "48c04c80-8e26-4e02-bbdb-78be37c1243e",
    "regionName" : "footer",
    "type" : "region"
  }, {
    "components" : [ {
      "componentAttributes" : {
        "customHeadTags" : "",
        "description" : "",
        "title" : "Contact Us"
      },
      "componentName" : "forceCommunity:seoAssistant",
      "id" : "3c20a266-4b42-45cb-a877-20114d925b99",
      "renditionMap" : { },
      "type" : "component"
    } ],
    "id" : "4222a1b0-2ab2-4a43-8c97-a610db88724c",
    "regionName" : "sfdcHiddenRegion",
    "type" : "region"
  } ],
  "themeLayoutType" : "Inner",
  "type" : "view",
  "viewType" : "contactsupport"
}